{
    "title": "Fortran",
    "url": "https://github.com/rabbiabram/awesome-fortran",
    "readme": "https://raw.githubusercontent.com/rabbiabram/awesome-fortran/master/README.md",
    "headingLevel": 2,
    "name": "fortran",
    "sections": [
        {
            "title": "Graphics Libraries",
            "name": "graphics-libraries"
        },
        {
            "title": "Math Libs",
            "name": "math-libs"
        },
        {
            "title": "JSON Manipulation",
            "name": "json-manipulation"
        },
        {
            "title": "XML Manipulation",
            "name": "xml-manipulation"
        },
        {
            "title": "Date and time manipulation",
            "name": "date-and-time-manipulation"
        },
        {
            "title": "Testing",
            "name": "testing"
        },
        {
            "title": "Fortran Websites",
            "name": "fortran-websites"
        },
        {
            "title": "Fortran Videos",
            "name": "fortran-videos"
        }
    ],
    "repoTitle": "Awesome Fortran",
    "data": "# Awesome Fortran\nA curated list of awesome Fortran frameworks, libraries and software. Inspired by [awesome-swift](https://github.com/Wolg/awesome-swift) by @Wolg.\n\n- [Awesome Fortran](#awesome-fortran)\n\t- [Graphics Libraries](#graphics-libraries)\n\t- [Math libs](#math-libs) \n\t- [JSON Manipulation](#json-manipulation)\n\t- [XML Manipulation](#xml-manipulation)\n\t- [Date and time manipulation](#date-and-time-manipulation)\n\t- [Testing](#testing)\n- [Resources](#resources)\n\t- [Fortran Videos](#fortran-videos)\n- [Other Awesome Lists](#other-awesome-lists)\n- [Contributing](#contributing)\n\n## Graphics Libraries\n*Libraries for graphing, graphics, and GUIs*\n\n* [DISLIN](http://www.mps.mpg.de/dislin/) - a high-level graphing and user-interface library.\n* [f90gl](http://math.nist.gov/f90gl/) - public domain implementation of the official NIST Fortran 90 bindings for OpenGL.\n* [F03GL](http://www-stone.ch.cam.ac.uk/pub/f03gl/index.xhtml) - a Fortran 2003 interface to the OpenGL library, along with the GLU and GLUT toolkits.\n* [gtk-fortran](https://github.com/jerryd/gtk-fortran/wiki) - a cross-platform library to build Graphical User Interfaces (GUI) using [GTK+](http://www.gtk.org/).  Very useful when combined with the [Glade](https://glade.gnome.org/) RAD tool.\n* [PGPLOT](http://www.astro.caltech.edu/~tjp/pgplot/) - cross-platform scientific graphing library.\n* [Xeffort](http://www.xeffort.com/) - open source library for building GUI applications in Intel Visual Fortran.\n\n## Math Libs\n*Libraries for calculatings and other mathematical operations.*\n\n* [BLAS](http://www.netlib.org/blas/) - application programming interface standard for publishing libraries to perform basic linear algebra operations such as vector and matrix multiplication.\n* [CERNLIB](http://cernlib.web.cern.ch/cernlib/) - The CERN Program Library is a large collection of general purpose libraries and modules maintained and offered in both source and object code form on the CERN central computers\n* [EISPACK](http://www.netlib.org/eispack/) - a software library for numerical computation of eigenvalues and eigenvectors of matrices, written in FORTRAN\n* [FGSL](http://www.lrz.de/services/software/mathematik/gsl/fortran/index.html) - portable, object-based Fortran interface to the [GNU scientific library](http://www.lrz.de/services/software/mathematik/gsl/)\n* [IMSL](http://www.roguewave.com/products/imsl-numerical-libraries/fortran-library.aspx) - The IMSL Fortran Numerical Library is the standard for high performance computing commercial mathematics and statistics libraries\n* [Lis](http://www.ssisc.org/lis/index.en.html#download) - a Library of Iterative Solvers for Linear Systems\n* [netCDF](https://github.com/Unidata/netcdf-fortran) - a set of software libraries and self-describing, machine-independent data formats that support the creation, access, and sharing of array-oriented scientific data.\n* [OpenBLAS](https://github.com/xianyi/OpenBLAS) - one of the fastest open source BLAS libraries available.  Almost as fast as Intel MKL.\n* [PAW](http://paw.web.cern.ch/paw/) - conceived as an instrument to assist physicists in the analysis and presentation of their data\n\n## JSON Manipulation\n*Libraries for JSON data manipulating with Fortran language.*\n\n* [FSON](https://github.com/josephalevin/fson) - Fortran 95 JSON Parser.\n* [json-fortran](https://github.com/jacobwilliams/json-fortran) - A Fortran 2008 JSON API.\n\n\n## XML Manipulation\n*Libraries for XML data manipulating with Fortran language.*\n\n* [fox](https://github.com/andreww/fox) - Fortran XML library\n* [xml-fortran](http://sourceforge.net/projects/xml-fortran/) - an all-Fortran solution for reading and writing XML files\n\n## Date and time manipulation\n*Libraries for date and time manipulation with Fortran language.*\n\n* [datetime-fortran](https://github.com/milancurcic/datetime-fortran) - A Fortran 2003 date and time manipulation library, modeled after Python's datetime library.\n\n## Testing\n*Libraries for testing codebases and generating test data.*\n\n* [FRUIT](http://sourceforge.net/projects/fortranxunit/) - FORTRAN Unit Test Framework, written in FORTRAN 95\n* [Ftunit](http://flibs.sourceforge.net/ftnunit.html) - Fortran unit testing framework by Arjen Markus\n* [pFUnit](http://sourceforge.net/projects/pfunit/) - Unit testing framework for Fortran with MPI extensions by developers from NASA and NGC TASC.  Uses parallel codes and object-oriented design.\n\n\n# Resources\nVarious resources, such as books, websites and articles, for improving your Fortran development skills and knowledge.\n\n## Fortran Websites\n\n* [The Fortran Company](http://www.fortran.com/) - A home page of FORTRAN programming language.\n* [Fortran Dev](http://fortrandev.wordpress.com) - Fortran development blog\n\n\n## Fortran Videos\n\n* [GNU FORTRAN Lesson 1](http://www.youtube.com/watch?v=qUy8M10uZRU) - Videos about the Fortran programming language.\n* [Modern Fortran for Scientists and Engineers](http://jolts.stanford.edu/72/modern_fortran_for_scientists_and_engineers) - Stanford JOLTS video tutorials on modern features of Fortran.\n\n\n# Other Awesome Lists\n\nOther amazingly awesome lists can be found in the [awesome-awesomeness](https://github.com/bayandin/awesome-awesomeness) list.\n\n# Contributing\n\nYour contributions are always welcome! Please submit a pull request or create an issue to add a new framework, library or software to the list. Do not submit a project, which hasn't been updated in the past 6 months or is not awesome.\n"
}